{
  "schema_version": 1,
  "generated_at": "2026-07-17T16:15:16.142364+00:00",
  "max_age_seconds": 7200,
  "run_id": "29595146234-1",
  "commit": "5964763ef321908a238a5f035608b0b54c41ea11",
  "status": "degraded",
  "publish_allowed": true,
  "checks": [
    {
      "name": "paper_all",
      "critical": true,
      "outcome": "success"
    },
    {
      "name": "agents_primary",
      "critical": true,
      "outcome": "success"
    },
    {
      "name": "portfolio_all",
      "critical": true,
      "outcome": "success"
    },
    {
      "name": "promote",
      "critical": true,
      "outcome": "success"
    },
    {
      "name": "exits",
      "critical": true,
      "outcome": "success"
    },
    {
      "name": "cot",
      "critical": false,
      "outcome": "success"
    },
    {
      "name": "agents_rr2",
      "critical": false,
      "outcome": "success"
    },
    {
      "name": "propr_manage",
      "critical": false,
      "outcome": "success"
    },
    {
      "name": "propr_guard",
      "critical": false,
      "outcome": "skipped"
    },
    {
      "name": "propr",
      "critical": false,
      "outcome": "success"
    },
    {
      "name": "polymarket",
      "critical": false,
      "outcome": "success"
    },
    {
      "name": "supabase",
      "critical": false,
      "outcome": "success"
    },
    {
      "name": "report",
      "critical": false,
      "outcome": "success"
    }
  ],
  "coverage": [
    {
      "schema_version": 1,
      "run_id": "29595146234-1",
      "generated_at": "2026-07-17T16:11:17.784396+00:00",
      "component": "agents-rr2-v1",
      "critical": false,
      "expected_count": 0,
      "observed_count": 0,
      "missing": [],
      "status": "pass"
    },
    {
      "schema_version": 1,
      "run_id": "29595146234-1",
      "generated_at": "2026-07-17T16:11:17.349307+00:00",
      "component": "agents-v1",
      "critical": true,
      "expected_count": 0,
      "observed_count": 0,
      "missing": [],
      "status": "pass"
    },
    {
      "schema_version": 1,
      "run_id": "29595146234-1",
      "generated_at": "2026-07-17T16:11:16.775987+00:00",
      "component": "commodities-trend-v1",
      "critical": true,
      "expected_count": 5,
      "observed_count": 5,
      "missing": [],
      "status": "pass"
    },
    {
      "schema_version": 1,
      "run_id": "29595146234-1",
      "generated_at": "2026-07-17T16:14:46.035970+00:00",
      "component": "exit-check",
      "critical": true,
      "expected_count": 2,
      "observed_count": 2,
      "missing": [],
      "status": "pass"
    },
    {
      "schema_version": 1,
      "run_id": "29595146234-1",
      "generated_at": "2026-07-17T16:14:42.353945+00:00",
      "component": "highvol-port-v1-prices",
      "critical": true,
      "expected_count": 139,
      "observed_count": 139,
      "missing": [],
      "status": "pass"
    },
    {
      "schema_version": 1,
      "run_id": "29595146234-1",
      "generated_at": "2026-07-17T16:14:42.354631+00:00",
      "component": "highvol-port-v1-signal-eligible",
      "critical": false,
      "expected_count": 135,
      "observed_count": 134,
      "missing": [
        "xyz:CXMT"
      ],
      "status": "fail"
    },
    {
      "schema_version": 1,
      "run_id": "29595146234-1",
      "generated_at": "2026-07-17T16:14:42.807788+00:00",
      "component": "liqimb-port-v1-prices",
      "critical": true,
      "expected_count": 9,
      "observed_count": 9,
      "missing": [],
      "status": "pass"
    },
    {
      "schema_version": 1,
      "run_id": "29595146234-1",
      "generated_at": "2026-07-17T16:14:42.808308+00:00",
      "component": "liqimb-port-v1-signal-eligible",
      "critical": true,
      "expected_count": 9,
      "observed_count": 9,
      "missing": [],
      "status": "pass"
    },
    {
      "schema_version": 1,
      "run_id": "29595146234-1",
      "generated_at": "2026-07-17T16:11:16.924192+00:00",
      "component": "paper-all",
      "critical": true,
      "expected_count": 1,
      "observed_count": 1,
      "missing": [],
      "status": "pass"
    },
    {
      "schema_version": 1,
      "run_id": "29595146234-1",
      "generated_at": "2026-07-17T16:14:42.889668+00:00",
      "component": "portfolio-all",
      "critical": true,
      "expected_count": 8,
      "observed_count": 8,
      "missing": [],
      "status": "pass"
    },
    {
      "schema_version": 1,
      "run_id": "29595146234-1",
      "generated_at": "2026-07-17T16:14:33.941323+00:00",
      "component": "tsmom-neutral-v1-prices",
      "critical": true,
      "expected_count": 139,
      "observed_count": 139,
      "missing": [],
      "status": "pass"
    },
    {
      "schema_version": 1,
      "run_id": "29595146234-1",
      "generated_at": "2026-07-17T16:14:33.942160+00:00",
      "component": "tsmom-neutral-v1-signal-eligible",
      "critical": false,
      "expected_count": 135,
      "observed_count": 133,
      "missing": [
        "CASHCAT",
        "xyz:CXMT"
      ],
      "status": "fail"
    },
    {
      "schema_version": 1,
      "run_id": "29595146234-1",
      "generated_at": "2026-07-17T16:14:34.430479+00:00",
      "component": "xsmom-highvol-combo-v1-prices",
      "critical": true,
      "expected_count": 135,
      "observed_count": 135,
      "missing": [],
      "status": "pass"
    },
    {
      "schema_version": 1,
      "run_id": "29595146234-1",
      "generated_at": "2026-07-17T16:14:34.431457+00:00",
      "component": "xsmom-highvol-combo-v1-signal-eligible",
      "critical": false,
      "expected_count": 135,
      "observed_count": 133,
      "missing": [
        "CASHCAT",
        "xyz:CXMT"
      ],
      "status": "fail"
    },
    {
      "schema_version": 1,
      "run_id": "29595146234-1",
      "generated_at": "2026-07-17T16:14:34.936060+00:00",
      "component": "xsmom-highvol-voltarget-v1-prices",
      "critical": true,
      "expected_count": 135,
      "observed_count": 135,
      "missing": [],
      "status": "pass"
    },
    {
      "schema_version": 1,
      "run_id": "29595146234-1",
      "generated_at": "2026-07-17T16:14:34.937280+00:00",
      "component": "xsmom-highvol-voltarget-v1-signal-eligible",
      "critical": false,
      "expected_count": 135,
      "observed_count": 133,
      "missing": [
        "CASHCAT",
        "xyz:CXMT"
      ],
      "status": "fail"
    },
    {
      "schema_version": 1,
      "run_id": "29595146234-1",
      "generated_at": "2026-07-17T16:14:29.002755+00:00",
      "component": "xsmom-multihorizon-v1-prices",
      "critical": true,
      "expected_count": 135,
      "observed_count": 135,
      "missing": [],
      "status": "pass"
    },
    {
      "schema_version": 1,
      "run_id": "29595146234-1",
      "generated_at": "2026-07-17T16:14:29.003390+00:00",
      "component": "xsmom-multihorizon-v1-signal-eligible",
      "critical": false,
      "expected_count": 135,
      "observed_count": 131,
      "missing": [
        "CASHCAT",
        "xyz:CXMT",
        "xyz:SHAZ",
        "xyz:SKHY"
      ],
      "status": "fail"
    },
    {
      "schema_version": 1,
      "run_id": "29595146234-1",
      "generated_at": "2026-07-17T16:14:38.427468+00:00",
      "component": "xsmom-port-v1-prices",
      "critical": true,
      "expected_count": 138,
      "observed_count": 138,
      "missing": [],
      "status": "pass"
    },
    {
      "schema_version": 1,
      "run_id": "29595146234-1",
      "generated_at": "2026-07-17T16:14:38.428192+00:00",
      "component": "xsmom-port-v1-signal-eligible",
      "critical": false,
      "expected_count": 135,
      "observed_count": 133,
      "missing": [
        "CASHCAT",
        "xyz:CXMT"
      ],
      "status": "fail"
    },
    {
      "schema_version": 1,
      "run_id": "29595146234-1",
      "generated_at": "2026-07-17T16:14:38.876488+00:00",
      "component": "xsmom-reb48-v1-prices",
      "critical": true,
      "expected_count": 135,
      "observed_count": 135,
      "missing": [],
      "status": "pass"
    },
    {
      "schema_version": 1,
      "run_id": "29595146234-1",
      "generated_at": "2026-07-17T16:14:38.877384+00:00",
      "component": "xsmom-reb48-v1-signal-eligible",
      "critical": false,
      "expected_count": 135,
      "observed_count": 133,
      "missing": [
        "CASHCAT",
        "xyz:CXMT"
      ],
      "status": "fail"
    }
  ],
  "required_coverage": [
    "paper-all",
    "agents-v1",
    "portfolio-all",
    "exit-check"
  ],
  "errors": [],
  "warnings": [
    "coverage:highvol-port-v1-signal-eligible",
    "coverage:tsmom-neutral-v1-signal-eligible",
    "coverage:xsmom-highvol-combo-v1-signal-eligible",
    "coverage:xsmom-highvol-voltarget-v1-signal-eligible",
    "coverage:xsmom-multihorizon-v1-signal-eligible",
    "coverage:xsmom-port-v1-signal-eligible",
    "coverage:xsmom-reb48-v1-signal-eligible"
  ],
  "validation_reasons": []
}
